similarwebact/__init__.py
similarwebact/__version__.py
similarwebact/similarweb.py
similarwebact-0.0.0.27.dist-info/METADATA
similarwebact-0.0.0.27.dist-info/WHEEL
similarwebact-0.0.0.27.dist-info/top_level.txt
similarwebact-0.0.0.27.dist-info/RECORD
