Metadata-Version: 2.1
Name: similarwebact
Version: 0.0.0.27
Summary: automation tool for similarweb
Home-page: https://github.com/SunkyeongLee/similarwebact
Author: Sunkyeong Lee
Author-email: sunkyeong.lee@concentrix.com
License: UNKNOWN
Platform: UNKNOWN
Classifier: Programming Language :: Python :: 3
Classifier: License :: OSI Approved :: MIT License
Classifier: Operating System :: OS Independent
Requires-Python: >=3.6
